{
  "items": [
    {
      "type": "group",
      "ctime": 1705242337934,
      "items": [
        {
          "type": "file",
          "ctime": 1705242379770,
          "path": "src/初等数学(高中数学)/函数-/基本函数-/三角函数_.md"
        },
        {
          "type": "file",
          "ctime": 1705242374252,
          "path": "src/初等数学(高中数学)/函数-/基本函数-/三角函数-/三角函数_公式.md"
        },
        {
          "type": "file",
          "ctime": 1705242383368,
          "path": "src/初等数学(高中数学)/函数-/基本函数-/三角函数-/三角函数_特殊值.md"
        },
        {
          "type": "file",
          "ctime": 1696250969886,
          "path": "src/微积分/-结论/泰勒公式.md"
        },
        {
          "type": "file",
          "ctime": 1705242396499,
          "path": "src/微积分/2_导数-/求导法则-/常数和基本初等函数的导数公式.md"
        },
        {
          "type": "file",
          "ctime": 1705129580990,
          "path": "src/微积分/3_积分-/积分表.md"
        },
        {
          "type": "file",
          "ctime": 1706281631646,
          "path": "src/初等数学(高中数学)/chaos/不等式.md"
        },
        {
          "type": "file",
          "ctime": 1709638637049,
          "path": "src/初等数学(高中数学)/chaos/实用的代数变换.md"
        },
        {
          "type": "file",
          "ctime": 1695813232846,
          "path": "src/初等数学(高中数学)/chaos/因式分解公式.md"
        },
        {
          "type": "file",
          "ctime": 1713948359919,
          "path": "src/符号&记号/二项式系数.md"
        }
      ],
      "title": "常用"
    },
    {
      "type": "group",
      "ctime": 1714104442859,
      "items": [
        {
          "type": "file",
          "ctime": 1714106270066,
          "path": "src/线性代数/--整理版/向量/判别线性相关性的结论.md"
        },
        {
          "type": "file",
          "ctime": 1714104485690,
          "path": "src/线性代数/矩阵与行列式/矩阵的基本运算/矩阵转置.md"
        },
        {
          "type": "file",
          "ctime": 1714104560056,
          "path": "src/线性代数/-术语/矩阵/伴随矩阵.md"
        },
        {
          "type": "file",
          "ctime": 1714104695901,
          "path": "src/线性代数/chaos/秩(rank).md"
        },
        {
          "type": "file",
          "ctime": 1714104478587,
          "path": "src/线性代数/矩阵与行列式/矩阵的基本运算/逆矩阵.md"
        },
        {
          "type": "file",
          "ctime": 1714105644109,
          "path": "src/线性代数/--整理版/特征值和特征向量/对角化.md"
        },
        {
          "type": "file",
          "ctime": 1714106013475,
          "path": "src/线性代数/矩阵与行列式/矩阵的基本运算/矩阵乘法.md"
        },
        {
          "type": "file",
          "ctime": 1714104472959,
          "path": "src/线性代数/矩阵与行列式/行列式/行列式的性质.md"
        }
      ],
      "title": "线代常用"
    },
    {
      "type": "group",
      "ctime": 1695813128929,
      "items": [
        {
          "type": "group",
          "ctime": 1695908602632,
          "items": [
            {
              "type": "group",
              "ctime": 1695813169954,
              "items": [
                {
                  "type": "file",
                  "ctime": 1695813164156,
                  "path": "src/初等数学(高中数学)/函数-/基本函数-/三角函数_.md"
                },
                {
                  "type": "file",
                  "ctime": 1695813193480,
                  "path": "src/初等数学(高中数学)/函数-/基本函数-/三角函数-/三角函数_公式推导.md"
                },
                {
                  "type": "file",
                  "ctime": 1695813193480,
                  "path": "src/初等数学(高中数学)/函数-/基本函数-/三角函数-/三角函数_公式.md"
                },
                {
                  "type": "file",
                  "ctime": 1695813193480,
                  "path": "src/初等数学(高中数学)/函数-/基本函数-/三角函数-/三角函数_特殊值.md"
                }
              ],
              "title": "三角函数"
            },
            {
              "type": "file",
              "ctime": 1695813221587,
              "path": "src/初等数学(高中数学)/数列/等差数列.md"
            },
            {
              "type": "file",
              "ctime": 1695813221587,
              "path": "src/初等数学(高中数学)/数列/等比数列.md"
            },
            {
              "type": "file",
              "ctime": 1695813221587,
              "path": "src/初等数学(高中数学)/数列/常见的数列前n项和.md"
            },
            {
              "type": "file",
              "ctime": 1695813186235,
              "path": "src/初等数学(高中数学)/函数-/基本函数-/指数函数 & 对数函数.md"
            },
            {
              "type": "file",
              "ctime": 1695813147548,
              "path": "src/运算法则/对数运算法则.md"
            },
            {
              "type": "file",
              "ctime": 1695821917186,
              "path": "src/初等数学(高中数学)/chaos/不等式.md"
            }
          ],
          "title": "-进行中"
        },
        {
          "type": "group",
          "ctime": 1695908926634,
          "items": [
            {
              "type": "file",
              "ctime": 1695813232846,
              "path": "src/初等数学(高中数学)/chaos/阶乘与双阶乘.md"
            },
            {
              "type": "file",
              "ctime": 1695813147548,
              "path": "src/运算法则/分数 运算法则.md"
            },
            {
              "type": "file",
              "ctime": 1695813147548,
              "path": "src/运算法则/幂(指数)运算法则.md"
            },
            {
              "type": "file",
              "ctime": 1695813147548,
              "path": "src/运算法则/指数运算法则.md"
            }
          ],
          "title": "-以熟悉"
        },
        {
          "type": "file",
          "ctime": 1695813232846,
          "path": "src/初等数学(高中数学)/chaos/一元二次方程.md"
        },
        {
          "type": "group",
          "ctime": 1696488841257,
          "items": [
            {
              "type": "file",
              "ctime": 1696488862714,
              "path": "src/初等数学(高中数学)/函数-/函数性质/有界性.md"
            },
            {
              "type": "file",
              "ctime": 1696488862714,
              "path": "src/初等数学(高中数学)/函数-/函数性质/奇偶性.md"
            },
            {
              "type": "file",
              "ctime": 1696488862714,
              "path": "src/初等数学(高中数学)/函数-/函数性质/单调性.md"
            },
            {
              "type": "file",
              "ctime": 1696488862714,
              "path": "src/初等数学(高中数学)/函数-/函数性质/凹凸性.md"
            },
            {
              "type": "file",
              "ctime": 1696488862714,
              "path": "src/初等数学(高中数学)/函数-/函数性质/周期性.md"
            }
          ],
          "title": "函数性质"
        },
        {
          "type": "group",
          "ctime": 1696488931187,
          "items": [
            {
              "type": "file",
              "ctime": 1696488959096,
              "path": "src/初等数学(高中数学)/chaos/恒等变形/通分.md"
            },
            {
              "type": "file",
              "ctime": 1696488959096,
              "path": "src/初等数学(高中数学)/chaos/恒等变形/提公因子.md"
            },
            {
              "type": "file",
              "ctime": 1696488959096,
              "path": "src/初等数学(高中数学)/chaos/恒等变形/换元.md"
            },
            {
              "type": "file",
              "ctime": 1696488959096,
              "path": "src/初等数学(高中数学)/chaos/恒等变形/分子有理化.md"
            },
            {
              "type": "file",
              "ctime": 1696488959096,
              "path": "src/初等数学(高中数学)/chaos/恒等变形/分母有理化.md"
            },
            {
              "type": "file",
              "ctime": 1696488959096,
              "path": "src/初等数学(高中数学)/chaos/恒等变形/约分.md"
            }
          ],
          "title": "恒等变形"
        }
      ],
      "title": "数学基础复习+背诵"
    },
    {
      "type": "group",
      "ctime": 1696250960175,
      "items": [
        {
          "type": "group",
          "ctime": 1696489487497,
          "items": [
            {
              "type": "group",
              "ctime": 1696489521212,
              "items": [
                {
                  "type": "file",
                  "ctime": 1696491300455,
                  "path": "src/微积分/1_极限/极限基础-/极限的存在准则.md"
                },
                {
                  "type": "file",
                  "ctime": 1696491755826,
                  "path": "src/微积分/1_极限/极限基础-/极限的定义.md"
                },
                {
                  "type": "file",
                  "ctime": 1696491645514,
                  "path": "src/微积分/1_极限/极限基础-/极限运算法则.md"
                },
                {
                  "type": "file",
                  "ctime": 1696491668608,
                  "path": "src/微积分/1_极限/极限基础-/两个重要的极限.md"
                },
                {
                  "type": "file",
                  "ctime": 1696489529793,
                  "path": "src/微积分/1_极限/极限基础-/函数极限的性质.md"
                },
                {
                  "type": "file",
                  "ctime": 1696493025294,
                  "path": "src/微积分/1_极限/连续性/连续点.md"
                },
                {
                  "type": "file",
                  "ctime": 1696493027863,
                  "path": "src/微积分/1_极限/连续性/间断点.md"
                },
                {
                  "type": "file",
                  "ctime": 1696493034019,
                  "path": "src/微积分/1_极限/连续性/连续性的性质.md"
                },
                {
                  "type": "file",
                  "ctime": 1696493013996,
                  "path": "src/微积分/1_极限/连续性/闭区间上连续函数的性质.md"
                },
                {
                  "type": "file",
                  "ctime": 1696505210477,
                  "path": "src/微积分/1_极限/无穷大/无穷大的性质.md"
                },
                {
                  "type": "file",
                  "ctime": 1696493966227,
                  "path": "src/微积分/1_极限/无穷大/无穷大比较.md"
                },
                {
                  "type": "file",
                  "ctime": 1696505506439,
                  "path": "src/微积分/1_极限/无穷小/无穷小.md"
                },
                {
                  "type": "file",
                  "ctime": 1696505511961,
                  "path": "src/微积分/1_极限/无穷小/无穷小的性质.md"
                },
                {
                  "type": "file",
                  "ctime": 1696506252874,
                  "path": "src/微积分/1_极限/-技巧/利用 有理运算法则 求极限.md"
                },
                {
                  "type": "file",
                  "ctime": 1696506244543,
                  "path": "src/微积分/1_极限/-技巧/利用 基本极限 求极限.md"
                },
                {
                  "type": "file",
                  "ctime": 1696506205087,
                  "path": "src/微积分/1_极限/-技巧/利用 等价无穷小代换 求极限.md"
                }
              ],
              "title": "极限系列"
            }
          ],
          "title": "-进行中"
        },
        {
          "type": "group",
          "ctime": 1696489501548,
          "items": [],
          "title": "-以完成"
        },
        {
          "type": "file",
          "ctime": 1696250972803,
          "path": "src/微积分/-结论/洛必达法则.md"
        }
      ],
      "title": "微积分背诵"
    },
    {
      "type": "group",
      "ctime": 1699876104031,
      "items": [
        {
          "type": "file",
          "ctime": 1700131224370,
          "path": "src/微积分/-术语/驻点(稳定点).md"
        },
        {
          "type": "file",
          "ctime": 1699876252582,
          "path": "src/微积分/-术语/渐近线/斜渐近线.md"
        },
        {
          "type": "file",
          "ctime": 1699876246841,
          "path": "src/微积分/-术语/渐近线/水平渐近线.md"
        },
        {
          "type": "file",
          "ctime": 1699876244698,
          "path": "src/微积分/-术语/渐近线/铅直渐近线.md"
        },
        {
          "type": "file",
          "ctime": 1699876238093,
          "path": "src/微积分/-术语/渐近线/渐近线.md"
        },
        {
          "type": "file",
          "ctime": 1699959726116,
          "path": "src/微积分/-术语/拐点/拐点的第三充分条件.md"
        },
        {
          "type": "file",
          "ctime": 1699876223515,
          "path": "src/微积分/-术语/拐点/拐点的第二充分条件.md"
        },
        {
          "type": "file",
          "ctime": 1699876221708,
          "path": "src/微积分/-术语/拐点/拐点的第一充分条件.md"
        },
        {
          "type": "file",
          "ctime": 1699876219301,
          "path": "src/微积分/-术语/拐点/拐点的必要条件.md"
        },
        {
          "type": "file",
          "ctime": 1699876216934,
          "path": "src/微积分/-术语/拐点.md"
        },
        {
          "type": "file",
          "ctime": 1699876194649,
          "path": "src/初等数学(高中数学)/函数-/函数性质/凹凸性.md"
        },
        {
          "type": "file",
          "ctime": 1699876156592,
          "path": "src/微积分/-术语/最值.md"
        },
        {
          "type": "file",
          "ctime": 1699939443468,
          "path": "src/微积分/-术语/极值/极值的第三充分条件.md"
        },
        {
          "type": "file",
          "ctime": 1699876141304,
          "path": "src/微积分/-术语/极值/极值的第二充分条件.md"
        },
        {
          "type": "file",
          "ctime": 1699876139352,
          "path": "src/微积分/-术语/极值/极值的第一充分条件.md"
        },
        {
          "type": "file",
          "ctime": 1699876137152,
          "path": "src/微积分/-术语/极值/极值的必要条件.md"
        },
        {
          "type": "file",
          "ctime": 1699876133795,
          "path": "src/微积分/-术语/极值.md"
        }
      ],
      "title": "一元函数微分学的几何应用"
    }
  ]
}