{
  "main": {
    "id": "84ee939e5cfa5fd6",
    "type": "split",
    "children": [
      {
        "id": "6ff35ebed64eb92c",
        "type": "tabs",
        "children": [
          {
            "id": "25a2f48c63e58da4",
            "type": "leaf",
            "state": {
              "type": "empty",
              "state": {}
            }
          }
        ]
      }
    ],
    "direction": "vertical"
  },
  "left": {
    "id": "174aa8e4a46c3767",
    "type": "split",
    "children": [
      {
        "id": "a15e1168a1eee83f",
        "type": "tabs",
        "children": [
          {
            "id": "fe0a6dddaba50f0c",
            "type": "leaf",
            "state": {
              "type": "file-explorer",
              "state": {
                "sortOrder": "alphabetical"
              }
            }
          },
          {
            "id": "a8c45b65a2cfc062",
            "type": "leaf",
            "state": {
              "type": "git-view",
              "state": {}
            }
          },
          {
            "id": "2284de68d834ed87",
            "type": "leaf",
            "state": {
              "type": "search",
              "state": {
                "query": "tag:#chaos",
                "matchingCase": false,
                "explainSearch": false,
                "collapseAll": false,
                "extraContext": false,
                "sortOrder": "alphabetical"
              }
            }
          },
          {
            "id": "8f42cb5075f9cc94",
            "type": "leaf",
            "state": {
              "type": "starred",
              "state": {}
            }
          }
        ]
      }
    ],
    "direction": "horizontal",
    "width": 311.5
  },
  "right": {
    "id": "6aa6a817b5e4c25e",
    "type": "split",
    "children": [
      {
        "id": "b36b82be6f751cee",
        "type": "tabs",
        "dimension": 53.61904761904762,
        "children": [
          {
            "id": "2542bcf1f6986c2e",
            "type": "leaf",
            "state": {
              "type": "backlink",
              "state": {
                "collapseAll": false,
                "extraContext": false,
                "sortOrder": "alphabetical",
                "showSearch": false,
                "searchQuery": "",
                "backlinkCollapsed": false,
                "unlinkedCollapsed": true
              }
            }
          },
          {
            "id": "37fea2f3856dd081",
            "type": "leaf",
            "state": {
              "type": "outgoing-link",
              "state": {
                "linksCollapsed": false,
                "unlinkedCollapsed": true
              }
            }
          },
          {
            "id": "6b2d71f8f9064ed9",
            "type": "leaf",
            "state": {
              "type": "outline",
              "state": {}
            }
          },
          {
            "id": "97f44c6d4ce34a07",
            "type": "leaf",
            "state": {
              "type": "calendar",
              "state": {}
            }
          },
          {
            "id": "5a4b5715474c26ae",
            "type": "leaf",
            "state": {
              "type": "advanced-tables-toolbar",
              "state": {}
            }
          },
          {
            "id": "858f2f9cfc07b4d0",
            "type": "leaf",
            "state": {
              "type": "graph",
              "state": {}
            }
          }
        ],
        "currentTab": 5
      },
      {
        "id": "aa9b6c7c010ecbfb",
        "type": "tabs",
        "dimension": 46.38095238095238,
        "children": [
          {
            "id": "3e8551d28bbfc98f",
            "type": "leaf",
            "state": {
              "type": "tag",
              "state": {
                "sortOrder": "frequency",
                "useHierarchy": true
              }
            }
          },
          {
            "id": "edbe402da21a6668",
            "type": "leaf",
            "state": {
              "type": "localgraph",
              "state": {
                "options": {
                  "collapse-filter": true,
                  "search": "",
                  "localJumps": 1,
                  "localBacklinks": true,
                  "localForelinks": true,
                  "localInterlinks": true,
                  "showTags": true,
                  "showAttachments": true,
                  "hideUnresolved": true,
                  "collapse-color-groups": true,
                  "colorGroups": [],
                  "collapse-display": false,
                  "showArrow": true,
                  "textFadeMultiplier": 0,
                  "nodeSizeMultiplier": 1,
                  "lineSizeMultiplier": 1,
                  "collapse-forces": false,
                  "centerStrength": 0.526041666666667,
                  "repelStrength": 10.9375,
                  "linkStrength": 0.578125,
                  "linkDistance": 270,
                  "scale": 0.8360386601669937,
                  "close": true
                }
              }
            }
          }
        ],
        "currentTab": 1
      }
    ],
    "direction": "horizontal",
    "width": 970.5
  },
  "left-ribbon": {
    "hiddenItems": {
      "canvas:新建白板": false,
      "switcher:打开快速切换": false,
      "graph:查看关系图谱": false,
      "daily-notes:打开/创建今天的日记": false,
      "templates:插入模板": false,
      "command-palette:打开命令面板": false,
      "table-editor-obsidian:Advanced Tables Toolbar": false,
      "templater-obsidian:Templater": false,
      "custom-sort:Toggle custom sorting": false
    }
  },
  "active": "25a2f48c63e58da4",
  "lastOpenFiles": [
    "src/微积分-/积分-/定积分-/定积分的应用.md",
    "src/微积分-/积分-/积分表.md",
    "src/微积分-/积分-/积分的性质.md",
    "src/微积分-/积分-/定积分-/定积分的概念.md",
    "src/微积分-/积分-/定积分-/牛顿-莱布尼兹公式.md",
    "src/微积分-/微分方程_.md",
    "src/微积分-/微分方程-/微分方程初步_.md",
    "README.md",
    "src/微积分-/微分方程-/微分方程初步-",
    "src/微积分-/微分方程-",
    "src/微积分-/积分-/不定积分-/原函数与不定积分的概念.md",
    "附件/330px-Fundamental_theorem_of_calculus_(animation).gif",
    "src/微积分-/导数-/导数基础-/导数定义.md",
    "附件/330px-Riemann.gif",
    "src/微积分-/定理&引理&法则&公式&...-/拉格朗日中值定理.md",
    "附件/数学分析新讲(1) (张筑生) (Z-Library).pdf",
    "chaos/chaos_1-/一堆记号.md",
    "src/微积分-/积分-/不定积分-/有理函数和可化为有理函数的不定积分.md",
    "src/微积分-/导数_.md",
    "src/微积分-/积分-/不定积分_.md",
    "src/微积分-/积分_.md",
    "src/微积分-/积分-",
    "src/微积分-/积分-/不定积分-/换元积分法与分部积分法.md",
    "chaos/chaos_1-/部分分式分解.md",
    "chaos/chaos_1-/因式分解.md",
    "src/术语-/系数.md",
    "src/符号&记号-/二项式系数.md",
    "src/术语-/有理函数(代数分数).md",
    "math_study_resource/books.md",
    "src/术语-/假分式.md",
    "src/术语-/真分式.md",
    "src/术语-/常量函数.md",
    "src/微积分-/积分-/定积分-",
    "附件/525px-Stationary_vs_inflection_pts.svg.png",
    "src/术语-/-微积分",
    "附件/Screenshot_20230316_215142.png",
    "附件/v2-2e7e7770abbc5ce0c78252f36020790a_720w.png",
    "附件/v2-1c30b1e760b346e1bd43a751d897c4eb_720w.webp",
    "附件/v2-4a53c5ad5def5cc5ae8865269224983b_720w.webp",
    "附件/v2-71f67f3cec16368723643c71d662f603_720w.jpg",
    "附件/数学分析（上册） 1 (华东师范大学数学系) (Z-Library).pdf",
    "src/微积分-/积分-/不定积分-",
    "未命名.canvas",
    "Idea-",
    "chaos/chaos_1_.canvas",
    "old_notion_chaos/2023_3_8迁移notion/术语&符号&概念&公式&…/术语&符号/Untitled/375px-Codomain2.SVG.png",
    "src/微积分-/定理&引理&法则&公式&...-",
    "附件/375px-Codomain2.SVG.png",
    "未命名 1.canvas"
  ]
}